scm203lab267101691/__init__.py
scm203lab267101691/lab2mod167101691.py
scm203lab267101691/lab2mod267101691.py
scm203lab267101691-0.1.1.dist-info/METADATA
scm203lab267101691-0.1.1.dist-info/WHEEL
scm203lab267101691-0.1.1.dist-info/top_level.txt
scm203lab267101691-0.1.1.dist-info/RECORD
