Metadata-Version: 2.4
Name: scm203lab267101691
Version: 0.1.1
Summary: Roots of equation and Differential equation
Home-page: https://github.com/khing2005/scm203lab267101691
Author: khing
Author-email: anchitha2005@gmail.com
Requires-Python: >=3.7
Dynamic: author
Dynamic: author-email
Dynamic: description
Dynamic: description-content-type
Dynamic: home-page
Dynamic: requires-python
Dynamic: summary
